{
  "pageCacheStats" : {
    "cachedChannelsStatistics" : {
      "hit" : 5542,
      "miss" : 0,
      "load" : 64,
      "capacity" : 400
    },
    "uncachedFileAccess" : 880,
    "maxRegisteredFiles" : 288,
    "maxCacheSizeInBytes" : 516521984,
    "totalCachedSizeInBytes" : 516521984,
    "pageHits" : 9212091,
    "pageFastCacheHits" : 27353013,
    "pageLoadsAboveSizeThreshold" : 0,
    "regularPageLoads" : 672,
    "disposedBuffers" : 3,
    "totalPageDisposalUs" : 29967,
    "totalPageLoadUs" : 1077159,
    "totalPagesLoaded" : 672,
    "capacityInBytes" : 524288000
  },
  "vfsStorageStats" : {
    "statsPerEnumerator" : {
      "contentHashes.dat" : {
        "collisions" : 0,
        "values" : 247,
        "dataFileSizeInBytes" : 4940,
        "storageSizeInBytes" : 96,
        "btreeStatistics" : {
          "pages" : 1,
          "elements" : 247,
          "height" : 1,
          "moves" : 0,
          "leafPages" : 1,
          "maxSearchStepsInRequest" : 2,
          "searchRequests" : 568,
          "searchSteps" : 26,
          "pageCapacity" : 32768,
          "sizeInBytes" : 32768
        }
      },
      "names.dat" : {
        "collisions" : 24,
        "values" : 127002,
        "dataFileSizeInBytes" : 2950641,
        "storageSizeInBytes" : 320,
        "btreeStatistics" : {
          "pages" : 63,
          "elements" : 126989,
          "height" : 2,
          "moves" : 875,
          "leafPages" : 62,
          "maxSearchStepsInRequest" : 69,
          "searchRequests" : 2704455,
          "searchSteps" : 4834187,
          "pageCapacity" : 32768,
          "sizeInBytes" : 2064384
        }
      }
    }
  },
  "indexStorageStats" : {
    "indexStoragesStats" : {
      "DomFileIndex" : {
        "statsPerPhm" : {
          "DomFileIndex.storage" : {
            "persistentEnumeratorStatistics" : {
              "collisions" : 0,
              "values" : 29,
              "dataFileSizeInBytes" : 690,
              "storageSizeInBytes" : 360,
              "btreeStatistics" : {
                "pages" : 1,
                "elements" : 29,
                "height" : 1,
                "moves" : 0,
                "leafPages" : 1,
                "maxSearchStepsInRequest" : 0,
                "searchRequests" : 72,
                "searchSteps" : 0,
                "pageCapacity" : 32768,
                "sizeInBytes" : 32768
              }
            },
            "valueStorageSizeInBytes" : 519
          },
          "DomFileIndex_inputs" : {
            "persistentEnumeratorStatistics" : {
              "collisions" : 0,
              "values" : 0,
              "dataFileSizeInBytes" : -1,
              "storageSizeInBytes" : 96,
              "btreeStatistics" : {
                "pages" : 1,
                "elements" : 92,
                "height" : 1,
                "moves" : 0,
                "leafPages" : 1,
                "maxSearchStepsInRequest" : 2,
                "searchRequests" : 675,
                "searchSteps" : 28,
                "pageCapacity" : 32768,
                "sizeInBytes" : 32768
              }
            },
            "valueStorageSizeInBytes" : 3547
          }
        }
      },
      "FrameworkDetectionIndex" : {
        "statsPerPhm" : {
          ".perFileVersion/indexed_versions/indexed_versions" : {
            "persistentEnumeratorStatistics" : {
              "collisions" : 0,
              "values" : 0,
              "dataFileSizeInBytes" : 0,
              "storageSizeInBytes" : 96,
              "btreeStatistics" : {
                "pages" : 0,
                "elements" : 0,
                "height" : 0,
                "moves" : 0,
                "leafPages" : 1,
                "maxSearchStepsInRequest" : 0,
                "searchRequests" : 0,
                "searchSteps" : 0,
                "pageCapacity" : 32768,
                "sizeInBytes" : 0
              }
            },
            "valueStorageSizeInBytes" : 0
          },
          "FrameworkDetectionIndex.storage" : {
            "persistentEnumeratorStatistics" : {
              "collisions" : 0,
              "values" : 0,
              "dataFileSizeInBytes" : 0,
              "storageSizeInBytes" : 96,
              "btreeStatistics" : {
                "pages" : 0,
                "elements" : 0,
                "height" : 0,
                "moves" : 0,
                "leafPages" : 1,
                "maxSearchStepsInRequest" : 0,
                "searchRequests" : 0,
                "searchSteps" : 0,
                "pageCapacity" : 32768,
                "sizeInBytes" : 0
              }
            },
            "valueStorageSizeInBytes" : 0
          },
          "FrameworkDetectionIndex_inputs" : {
            "persistentEnumeratorStatistics" : {
              "collisions" : 0,
              "values" : 0,
              "dataFileSizeInBytes" : -1,
              "storageSizeInBytes" : 96,
              "btreeStatistics" : {
                "pages" : 0,
                "elements" : 0,
                "height" : 0,
                "moves" : 0,
                "leafPages" : 1,
                "maxSearchStepsInRequest" : 0,
                "searchRequests" : 0,
                "searchSteps" : 0,
                "pageCapacity" : 32768,
                "sizeInBytes" : 0
              }
            },
            "valueStorageSizeInBytes" : 0
          }
        }
      },
      "IdIndex" : {
        "statsPerPhm" : {
          ".perFileVersion/indexed_versions/indexed_versions" : {
            "persistentEnumeratorStatistics" : {
              "collisions" : 0,
              "values" : 22,
              "dataFileSizeInBytes" : 1385,
              "storageSizeInBytes" : 304,
              "btreeStatistics" : {
                "pages" : 1,
                "elements" : 22,
                "height" : 1,
                "moves" : 0,
                "leafPages" : 1,
                "maxSearchStepsInRequest" : 0,
                "searchRequests" : 116,
                "searchSteps" : 0,
                "pageCapacity" : 32768,
                "sizeInBytes" : 32768
              }
            },
            "valueStorageSizeInBytes" : 181
          },
          "IdIndex.storage" : {
            "persistentEnumeratorStatistics" : {
              "collisions" : 0,
              "values" : 0,
              "dataFileSizeInBytes" : -1,
              "storageSizeInBytes" : 96,
              "btreeStatistics" : {
                "pages" : 2995,
                "elements" : 7827607,
                "height" : 2,
                "moves" : 2237483,
                "leafPages" : 2994,
                "maxSearchStepsInRequest" : 360,
                "searchRequests" : 148161089,
                "searchSteps" : 97364338,
                "pageCapacity" : 32768,
                "sizeInBytes" : 98140160
              }
            },
            "valueStorageSizeInBytes" : 680189745
          },
          "IdIndex_inputs" : {
            "persistentEnumeratorStatistics" : {
              "collisions" : 0,
              "values" : 0,
              "dataFileSizeInBytes" : -1,
              "storageSizeInBytes" : 96,
              "btreeStatistics" : {
                "pages" : 25,
                "elements" : 49270,
                "height" : 2,
                "moves" : 85,
                "leafPages" : 24,
                "maxSearchStepsInRequest" : 210,
                "searchRequests" : 270928,
                "searchSteps" : 566213,
                "pageCapacity" : 32768,
                "sizeInBytes" : 819200
              }
            },
            "valueStorageSizeInBytes" : 145030699
          }
        }
      },
      "Py.class.attributes" : {
        "statsPerPhm" : {
          "Py.class.attributes.storage" : {
            "persistentEnumeratorStatistics" : {
              "collisions" : 25,
              "values" : 69946,
              "dataFileSizeInBytes" : 1164596,
              "storageSizeInBytes" : 564880,
              "btreeStatistics" : {
                "pages" : 33,
                "elements" : 69933,
                "height" : 2,
                "moves" : 226,
                "leafPages" : 32,
                "maxSearchStepsInRequest" : 69,
                "searchRequests" : 551377,
                "searchSteps" : 576967,
                "pageCapacity" : 32768,
                "sizeInBytes" : 1081344
              }
            },
            "valueStorageSizeInBytes" : 3538773
          }
        }
      },
      "Py.class.shortName" : {
        "statsPerPhm" : {
          "Py.class.shortName.storage" : {
            "persistentEnumeratorStatistics" : {
              "collisions" : 10,
              "values" : 23748,
              "dataFileSizeInBytes" : 372623,
              "storageSizeInBytes" : 194576,
              "btreeStatistics" : {
                "pages" : 9,
                "elements" : 23743,
                "height" : 2,
                "moves" : 12,
                "leafPages" : 8,
                "maxSearchStepsInRequest" : 67,
                "searchRequests" : 153898,
                "searchSteps" : 181422,
                "pageCapacity" : 32768,
                "sizeInBytes" : 294912
              }
            },
            "valueStorageSizeInBytes" : 917490
          }
        }
      },
      "Py.class.shortNameInsensitive" : {
        "statsPerPhm" : {
          "Py.class.shortNameInsensitive.storage" : {
            "persistentEnumeratorStatistics" : {
              "collisions" : 8,
              "values" : 23520,
              "dataFileSizeInBytes" : 370792,
              "storageSizeInBytes" : 192752,
              "btreeStatistics" : {
                "pages" : 9,
                "elements" : 23516,
                "height" : 2,
                "moves" : 13,
                "leafPages" : 8,
                "maxSearchStepsInRequest" : 74,
                "searchRequests" : 152776,
                "searchSteps" : 183701,
                "pageCapacity" : 32768,
                "sizeInBytes" : 294912
              }
            },
            "valueStorageSizeInBytes" : 917483
          }
        }
      },
      "Py.class.super" : {
        "statsPerPhm" : {
          "Py.class.super.storage" : {
            "persistentEnumeratorStatistics" : {
              "collisions" : 2,
              "values" : 4233,
              "dataFileSizeInBytes" : 60406,
              "storageSizeInBytes" : 38152,
              "btreeStatistics" : {
                "pages" : 3,
                "elements" : 4232,
                "height" : 2,
                "moves" : 0,
                "leafPages" : 2,
                "maxSearchStepsInRequest" : 57,
                "searchRequests" : 32439,
                "searchSteps" : 22148,
                "pageCapacity" : 32768,
                "sizeInBytes" : 98304
              }
            },
            "valueStorageSizeInBytes" : 327677
          }
        }
      },
      "Py.module.attribute" : {
        "statsPerPhm" : {
          "Py.module.attribute.storage" : {
            "persistentEnumeratorStatistics" : {
              "collisions" : 38,
              "values" : 86264,
              "dataFileSizeInBytes" : 1522526,
              "storageSizeInBytes" : 695680,
              "btreeStatistics" : {
                "pages" : 33,
                "elements" : 86245,
                "height" : 2,
                "moves" : 219,
                "leafPages" : 32,
                "maxSearchStepsInRequest" : 92,
                "searchRequests" : 577355,
                "searchSteps" : 609162,
                "pageCapacity" : 32768,
                "sizeInBytes" : 1081344
              }
            },
            "valueStorageSizeInBytes" : 3244027
          }
        }
      },
      "Py.module.name" : {
        "statsPerPhm" : {
          "Py.module.name.storage" : {
            "persistentEnumeratorStatistics" : {
              "collisions" : 0,
              "values" : 4110,
              "dataFileSizeInBytes" : 47216,
              "storageSizeInBytes" : 33072,
              "btreeStatistics" : {
                "pages" : 3,
                "elements" : 4110,
                "height" : 2,
                "moves" : 0,
                "leafPages" : 2,
                "maxSearchStepsInRequest" : 47,
                "searchRequests" : 28514,
                "searchSteps" : 29884,
                "pageCapacity" : 32768,
                "sizeInBytes" : 98304
              }
            },
            "valueStorageSizeInBytes" : 294890
          },
          "Py.module.name_inputs" : {
            "persistentEnumeratorStatistics" : {
              "collisions" : 0,
              "values" : 0,
              "dataFileSizeInBytes" : -1,
              "storageSizeInBytes" : 96,
              "btreeStatistics" : {
                "pages" : 21,
                "elements" : 41556,
                "height" : 2,
                "moves" : 26,
                "leafPages" : 20,
                "maxSearchStepsInRequest" : 128,
                "searchRequests" : 199889,
                "searchSteps" : 343454,
                "pageCapacity" : 32768,
                "sizeInBytes" : 688128
              }
            },
            "valueStorageSizeInBytes" : 622574
          }
        }
      },
      "Py.setuptools.namespace" : {
        "statsPerPhm" : {
          "Py.setuptools.namespace.storage" : {
            "persistentEnumeratorStatistics" : {
              "collisions" : 0,
              "values" : 0,
              "dataFileSizeInBytes" : 0,
              "storageSizeInBytes" : 96,
              "btreeStatistics" : {
                "pages" : 0,
                "elements" : 0,
                "height" : 0,
                "moves" : 0,
                "leafPages" : 1,
                "maxSearchStepsInRequest" : 0,
                "searchRequests" : 0,
                "searchSteps" : 0,
                "pageCapacity" : 32768,
                "sizeInBytes" : 0
              }
            },
            "valueStorageSizeInBytes" : 0
          },
          "Py.setuptools.namespace_inputs" : {
            "persistentEnumeratorStatistics" : {
              "collisions" : 0,
              "values" : 0,
              "dataFileSizeInBytes" : -1,
              "storageSizeInBytes" : 96,
              "btreeStatistics" : {
                "pages" : 0,
                "elements" : 0,
                "height" : 0,
                "moves" : 0,
                "leafPages" : 1,
                "maxSearchStepsInRequest" : 0,
                "searchRequests" : 0,
                "searchSteps" : 0,
                "pageCapacity" : 32768,
                "sizeInBytes" : 0
              }
            },
            "valueStorageSizeInBytes" : 0
          }
        }
      },
      "Py.variable.shortName" : {
        "statsPerPhm" : {
          "Py.variable.shortName.storage" : {
            "persistentEnumeratorStatistics" : {
              "collisions" : 26,
              "values" : 45326,
              "dataFileSizeInBytes" : 848376,
              "storageSizeInBytes" : 367536,
              "btreeStatistics" : {
                "pages" : 17,
                "elements" : 45313,
                "height" : 2,
                "moves" : 55,
                "leafPages" : 16,
                "maxSearchStepsInRequest" : 51,
                "searchRequests" : 277378,
                "searchSteps" : 320633,
                "pageCapacity" : 32768,
                "sizeInBytes" : 557056
              }
            },
            "valueStorageSizeInBytes" : 1540095
          }
        }
      },
      "Python.Decorator" : {
        "statsPerPhm" : {
          "Python.Decorator.storage" : {
            "persistentEnumeratorStatistics" : {
              "collisions" : 0,
              "values" : 1509,
              "dataFileSizeInBytes" : 27227,
              "storageSizeInBytes" : 12216,
              "btreeStatistics" : {
                "pages" : 1,
                "elements" : 1509,
                "height" : 1,
                "moves" : 0,
                "leafPages" : 1,
                "maxSearchStepsInRequest" : 5,
                "searchRequests" : 9665,
                "searchSteps" : 1801,
                "pageCapacity" : 32768,
                "sizeInBytes" : 32768
              }
            },
            "valueStorageSizeInBytes" : 131002
          }
        }
      },
      "RelaxSymbolIndex" : {
        "statsPerPhm" : {
          "RelaxSymbolIndex.storage" : {
            "persistentEnumeratorStatistics" : {
              "collisions" : 0,
              "values" : 0,
              "dataFileSizeInBytes" : 0,
              "storageSizeInBytes" : 96,
              "btreeStatistics" : {
                "pages" : 0,
                "elements" : 0,
                "height" : 0,
                "moves" : 0,
                "leafPages" : 1,
                "maxSearchStepsInRequest" : 0,
                "searchRequests" : 0,
                "searchSteps" : 0,
                "pageCapacity" : 32768,
                "sizeInBytes" : 0
              }
            },
            "valueStorageSizeInBytes" : 0
          },
          "RelaxSymbolIndex_inputs" : {
            "persistentEnumeratorStatistics" : {
              "collisions" : 0,
              "values" : 0,
              "dataFileSizeInBytes" : -1,
              "storageSizeInBytes" : 96,
              "btreeStatistics" : {
                "pages" : 0,
                "elements" : 0,
                "height" : 0,
                "moves" : 0,
                "leafPages" : 1,
                "maxSearchStepsInRequest" : 0,
                "searchRequests" : 0,
                "searchSteps" : 0,
                "pageCapacity" : 32768,
                "sizeInBytes" : 0
              }
            },
            "valueStorageSizeInBytes" : 0
          }
        }
      },
      "SchemaTypeInheritance" : {
        "statsPerPhm" : {
          "SchemaTypeInheritance.storage" : {
            "persistentEnumeratorStatistics" : {
              "collisions" : 0,
              "values" : 62,
              "dataFileSizeInBytes" : 2781,
              "storageSizeInBytes" : 624,
              "btreeStatistics" : {
                "pages" : 1,
                "elements" : 62,
                "height" : 1,
                "moves" : 0,
                "leafPages" : 1,
                "maxSearchStepsInRequest" : 0,
                "searchRequests" : 127,
                "searchSteps" : 0,
                "pageCapacity" : 32768,
                "sizeInBytes" : 32768
              }
            },
            "valueStorageSizeInBytes" : 12995
          },
          "SchemaTypeInheritance_inputs" : {
            "persistentEnumeratorStatistics" : {
              "collisions" : 0,
              "values" : 0,
              "dataFileSizeInBytes" : -1,
              "storageSizeInBytes" : 96,
              "btreeStatistics" : {
                "pages" : 1,
                "elements" : 9,
                "height" : 1,
                "moves" : 0,
                "leafPages" : 1,
                "maxSearchStepsInRequest" : 0,
                "searchRequests" : 405,
                "searchSteps" : 0,
                "pageCapacity" : 32768,
                "sizeInBytes" : 32768
              }
            },
            "valueStorageSizeInBytes" : 19356
          }
        }
      },
      "Stubs" : {
        "statsPerPhm" : {
          ".perFileVersion/indexed_versions/indexed_versions" : {
            "persistentEnumeratorStatistics" : {
              "collisions" : 0,
              "values" : 6,
              "dataFileSizeInBytes" : 170,
              "storageSizeInBytes" : 176,
              "btreeStatistics" : {
                "pages" : 1,
                "elements" : 6,
                "height" : 1,
                "moves" : 0,
                "leafPages" : 1,
                "maxSearchStepsInRequest" : 0,
                "searchRequests" : 40,
                "searchSteps" : 0,
                "pageCapacity" : 32768,
                "sizeInBytes" : 32768
              }
            },
            "valueStorageSizeInBytes" : 85
          },
          "Stubs.storage" : {
            "persistentEnumeratorStatistics" : {
              "collisions" : 0,
              "values" : 0,
              "dataFileSizeInBytes" : -1,
              "storageSizeInBytes" : 96,
              "btreeStatistics" : {
                "pages" : 19,
                "elements" : 37529,
                "height" : 2,
                "moves" : 63,
                "leafPages" : 18,
                "maxSearchStepsInRequest" : 105,
                "searchRequests" : 213277,
                "searchSteps" : 452949,
                "pageCapacity" : 32768,
                "sizeInBytes" : 622592
              }
            },
            "valueStorageSizeInBytes" : 147235510
          },
          "py.function.shortname/Py.function.shortName.storage" : {
            "persistentEnumeratorStatistics" : {
              "collisions" : 16,
              "values" : 69735,
              "dataFileSizeInBytes" : 1229545,
              "storageSizeInBytes" : 563192,
              "btreeStatistics" : {
                "pages" : 33,
                "elements" : 69727,
                "height" : 2,
                "moves" : 218,
                "leafPages" : 32,
                "maxSearchStepsInRequest" : 70,
                "searchRequests" : 517139,
                "searchSteps" : 548825,
                "pageCapacity" : 32768,
                "sizeInBytes" : 1081344
              }
            },
            "valueStorageSizeInBytes" : 3047238
          }
        }
      },
      "TodoIndex" : {
        "statsPerPhm" : {
          ".perFileVersion/indexed_versions/indexed_versions" : {
            "persistentEnumeratorStatistics" : {
              "collisions" : 0,
              "values" : 0,
              "dataFileSizeInBytes" : 0,
              "storageSizeInBytes" : 96,
              "btreeStatistics" : {
                "pages" : 0,
                "elements" : 0,
                "height" : 0,
                "moves" : 0,
                "leafPages" : 1,
                "maxSearchStepsInRequest" : 0,
                "searchRequests" : 0,
                "searchSteps" : 0,
                "pageCapacity" : 32768,
                "sizeInBytes" : 0
              }
            },
            "valueStorageSizeInBytes" : 0
          },
          "TodoIndex.storage" : {
            "persistentEnumeratorStatistics" : {
              "collisions" : 0,
              "values" : 0,
              "dataFileSizeInBytes" : -1,
              "storageSizeInBytes" : 96,
              "btreeStatistics" : {
                "pages" : 0,
                "elements" : 0,
                "height" : 0,
                "moves" : 0,
                "leafPages" : 1,
                "maxSearchStepsInRequest" : 0,
                "searchRequests" : 0,
                "searchSteps" : 0,
                "pageCapacity" : 32768,
                "sizeInBytes" : 0
              }
            },
            "valueStorageSizeInBytes" : 0
          }
        }
      },
      "Trigram.Index" : {
        "statsPerPhm" : {
          "Trigram.Index.storage" : {
            "persistentEnumeratorStatistics" : {
              "collisions" : 0,
              "values" : 0,
              "dataFileSizeInBytes" : -1,
              "storageSizeInBytes" : 96,
              "btreeStatistics" : {
                "pages" : 680,
                "elements" : 1746517,
                "height" : 2,
                "moves" : 94600,
                "leafPages" : 679,
                "maxSearchStepsInRequest" : 454,
                "searchRequests" : 115001699,
                "searchSteps" : 89886325,
                "pageCapacity" : 32768,
                "sizeInBytes" : 22282240
              }
            },
            "valueStorageSizeInBytes" : 527260993
          },
          "Trigram.Index_inputs" : {
            "persistentEnumeratorStatistics" : {
              "collisions" : 0,
              "values" : 0,
              "dataFileSizeInBytes" : -1,
              "storageSizeInBytes" : 96,
              "btreeStatistics" : {
                "pages" : 25,
                "elements" : 49244,
                "height" : 2,
                "moves" : 85,
                "leafPages" : 24,
                "maxSearchStepsInRequest" : 210,
                "searchRequests" : 271310,
                "searchSteps" : 567574,
                "pageCapacity" : 32768,
                "sizeInBytes" : 819200
              }
            },
            "valueStorageSizeInBytes" : 96834862
          }
        }
      },
      "XmlNamespaces" : {
        "statsPerPhm" : {
          "XmlNamespaces.storage" : {
            "persistentEnumeratorStatistics" : {
              "collisions" : 0,
              "values" : 9,
              "dataFileSizeInBytes" : 351,
              "storageSizeInBytes" : 200,
              "btreeStatistics" : {
                "pages" : 1,
                "elements" : 9,
                "height" : 1,
                "moves" : 0,
                "leafPages" : 1,
                "maxSearchStepsInRequest" : 0,
                "searchRequests" : 18,
                "searchSteps" : 0,
                "pageCapacity" : 32768,
                "sizeInBytes" : 32768
              }
            },
            "valueStorageSizeInBytes" : 5260
          },
          "XmlNamespaces_inputs" : {
            "persistentEnumeratorStatistics" : {
              "collisions" : 0,
              "values" : 0,
              "dataFileSizeInBytes" : -1,
              "storageSizeInBytes" : 96,
              "btreeStatistics" : {
                "pages" : 1,
                "elements" : 14,
                "height" : 1,
                "moves" : 0,
                "leafPages" : 1,
                "maxSearchStepsInRequest" : 0,
                "searchRequests" : 418,
                "searchSteps" : 0,
                "pageCapacity" : 32768,
                "sizeInBytes" : 32768
              }
            },
            "valueStorageSizeInBytes" : 5754
          }
        }
      },
      "XmlTagNames" : {
        "statsPerPhm" : {
          "XmlTagNames.storage" : {
            "persistentEnumeratorStatistics" : {
              "collisions" : 0,
              "values" : 190,
              "dataFileSizeInBytes" : 1519,
              "storageSizeInBytes" : 1648,
              "btreeStatistics" : {
                "pages" : 1,
                "elements" : 190,
                "height" : 1,
                "moves" : 0,
                "leafPages" : 1,
                "maxSearchStepsInRequest" : 1,
                "searchRequests" : 387,
                "searchSteps" : 10,
                "pageCapacity" : 32768,
                "sizeInBytes" : 32768
              }
            },
            "valueStorageSizeInBytes" : 1670
          },
          "XmlTagNames_inputs" : {
            "persistentEnumeratorStatistics" : {
              "collisions" : 0,
              "values" : 0,
              "dataFileSizeInBytes" : -1,
              "storageSizeInBytes" : 96,
              "btreeStatistics" : {
                "pages" : 1,
                "elements" : 7,
                "height" : 1,
                "moves" : 0,
                "leafPages" : 1,
                "maxSearchStepsInRequest" : 0,
                "searchRequests" : 400,
                "searchSteps" : 0,
                "pageCapacity" : 32768,
                "sizeInBytes" : 32768
              }
            },
            "valueStorageSizeInBytes" : 2494
          }
        }
      },
      "dom.elementClass" : {
        "statsPerPhm" : {
          "dom.elementClass.storage" : {
            "persistentEnumeratorStatistics" : {
              "collisions" : 0,
              "values" : 0,
              "dataFileSizeInBytes" : 0,
              "storageSizeInBytes" : 96,
              "btreeStatistics" : {
                "pages" : 0,
                "elements" : 0,
                "height" : 0,
                "moves" : 0,
                "leafPages" : 1,
                "maxSearchStepsInRequest" : 0,
                "searchRequests" : 0,
                "searchSteps" : 0,
                "pageCapacity" : 32768,
                "sizeInBytes" : 0
              }
            },
            "valueStorageSizeInBytes" : 0
          }
        }
      },
      "dom.namespaceKey" : {
        "statsPerPhm" : {
          "dom.namespaceKey.storage" : {
            "persistentEnumeratorStatistics" : {
              "collisions" : 0,
              "values" : 0,
              "dataFileSizeInBytes" : 0,
              "storageSizeInBytes" : 96,
              "btreeStatistics" : {
                "pages" : 0,
                "elements" : 0,
                "height" : 0,
                "moves" : 0,
                "leafPages" : 1,
                "maxSearchStepsInRequest" : 0,
                "searchRequests" : 0,
                "searchSteps" : 0,
                "pageCapacity" : 32768,
                "sizeInBytes" : 0
              }
            },
            "valueStorageSizeInBytes" : 0
          }
        }
      },
      "editorconfig.index.name" : {
        "statsPerPhm" : {
          "editorconfig.index.name.storage" : {
            "persistentEnumeratorStatistics" : {
              "collisions" : 0,
              "values" : 0,
              "dataFileSizeInBytes" : 0,
              "storageSizeInBytes" : 96,
              "btreeStatistics" : {
                "pages" : 0,
                "elements" : 0,
                "height" : 0,
                "moves" : 0,
                "leafPages" : 1,
                "maxSearchStepsInRequest" : 0,
                "searchRequests" : 0,
                "searchSteps" : 0,
                "pageCapacity" : 32768,
                "sizeInBytes" : 0
              }
            },
            "valueStorageSizeInBytes" : 0
          },
          "editorconfig.index.name_inputs" : {
            "persistentEnumeratorStatistics" : {
              "collisions" : 0,
              "values" : 0,
              "dataFileSizeInBytes" : -1,
              "storageSizeInBytes" : 96,
              "btreeStatistics" : {
                "pages" : 0,
                "elements" : 0,
                "height" : 0,
                "moves" : 0,
                "leafPages" : 1,
                "maxSearchStepsInRequest" : 0,
                "searchRequests" : 0,
                "searchSteps" : 0,
                "pageCapacity" : 32768,
                "sizeInBytes" : 0
              }
            },
            "valueStorageSizeInBytes" : 0
          }
        }
      },
      "fileIncludes" : {
        "statsPerPhm" : {
          ".perFileVersion/indexed_versions/indexed_versions" : {
            "persistentEnumeratorStatistics" : {
              "collisions" : 0,
              "values" : 1,
              "dataFileSizeInBytes" : 23,
              "storageSizeInBytes" : 136,
              "btreeStatistics" : {
                "pages" : 1,
                "elements" : 1,
                "height" : 1,
                "moves" : 0,
                "leafPages" : 1,
                "maxSearchStepsInRequest" : 0,
                "searchRequests" : 7,
                "searchSteps" : 0,
                "pageCapacity" : 32768,
                "sizeInBytes" : 32768
              }
            },
            "valueStorageSizeInBytes" : 55
          },
          "fileIncludes.storage" : {
            "persistentEnumeratorStatistics" : {
              "collisions" : 0,
              "values" : 0,
              "dataFileSizeInBytes" : 0,
              "storageSizeInBytes" : 96,
              "btreeStatistics" : {
                "pages" : 0,
                "elements" : 0,
                "height" : 0,
                "moves" : 0,
                "leafPages" : 1,
                "maxSearchStepsInRequest" : 0,
                "searchRequests" : 0,
                "searchSteps" : 0,
                "pageCapacity" : 32768,
                "sizeInBytes" : 0
              }
            },
            "valueStorageSizeInBytes" : 0
          },
          "fileIncludes_inputs" : {
            "persistentEnumeratorStatistics" : {
              "collisions" : 0,
              "values" : 0,
              "dataFileSizeInBytes" : -1,
              "storageSizeInBytes" : 96,
              "btreeStatistics" : {
                "pages" : 0,
                "elements" : 0,
                "height" : 0,
                "moves" : 0,
                "leafPages" : 1,
                "maxSearchStepsInRequest" : 0,
                "searchRequests" : 0,
                "searchSteps" : 0,
                "pageCapacity" : 32768,
                "sizeInBytes" : 0
              }
            },
            "valueStorageSizeInBytes" : 0
          }
        }
      },
      "html5.custom.attributes.index" : {
        "statsPerPhm" : {
          "html5.custom.attributes.index.storage" : {
            "persistentEnumeratorStatistics" : {
              "collisions" : 0,
              "values" : 31,
              "dataFileSizeInBytes" : 546,
              "storageSizeInBytes" : 376,
              "btreeStatistics" : {
                "pages" : 1,
                "elements" : 31,
                "height" : 1,
                "moves" : 0,
                "leafPages" : 1,
                "maxSearchStepsInRequest" : 0,
                "searchRequests" : 95,
                "searchSteps" : 0,
                "pageCapacity" : 32768,
                "sizeInBytes" : 32768
              }
            },
            "valueStorageSizeInBytes" : 594
          },
          "html5.custom.attributes.index_inputs" : {
            "persistentEnumeratorStatistics" : {
              "collisions" : 0,
              "values" : 0,
              "dataFileSizeInBytes" : -1,
              "storageSizeInBytes" : 96,
              "btreeStatistics" : {
                "pages" : 1,
                "elements" : 84,
                "height" : 1,
                "moves" : 0,
                "leafPages" : 1,
                "maxSearchStepsInRequest" : 1,
                "searchRequests" : 649,
                "searchSteps" : 1,
                "pageCapacity" : 32768,
                "sizeInBytes" : 32768
              }
            },
            "valueStorageSizeInBytes" : 2405
          }
        }
      },
      "json.file.root.values" : {
        "statsPerPhm" : {
          "json.file.root.values.storage" : {
            "persistentEnumeratorStatistics" : {
              "collisions" : 0,
              "values" : 3,
              "dataFileSizeInBytes" : 63,
              "storageSizeInBytes" : 152,
              "btreeStatistics" : {
                "pages" : 1,
                "elements" : 3,
                "height" : 1,
                "moves" : 0,
                "leafPages" : 1,
                "maxSearchStepsInRequest" : 0,
                "searchRequests" : 245,
                "searchSteps" : 0,
                "pageCapacity" : 32768,
                "sizeInBytes" : 32768
              }
            },
            "valueStorageSizeInBytes" : 9066
          },
          "json.file.root.values_inputs" : {
            "persistentEnumeratorStatistics" : {
              "collisions" : 0,
              "values" : 0,
              "dataFileSizeInBytes" : -1,
              "storageSizeInBytes" : 96,
              "btreeStatistics" : {
                "pages" : 1,
                "elements" : 1216,
                "height" : 1,
                "moves" : 0,
                "leafPages" : 1,
                "maxSearchStepsInRequest" : 5,
                "searchRequests" : 4079,
                "searchSteps" : 1184,
                "pageCapacity" : 32768,
                "sizeInBytes" : 32768
              }
            },
            "valueStorageSizeInBytes" : 116457
          }
        }
      },
      "markdown.header" : {
        "statsPerPhm" : {
          "markdown.header.storage" : {
            "persistentEnumeratorStatistics" : {
              "collisions" : 0,
              "values" : 1771,
              "dataFileSizeInBytes" : 51892,
              "storageSizeInBytes" : 14320,
              "btreeStatistics" : {
                "pages" : 1,
                "elements" : 1771,
                "height" : 1,
                "moves" : 0,
                "leafPages" : 1,
                "maxSearchStepsInRequest" : 6,
                "searchRequests" : 5334,
                "searchSteps" : 1948,
                "pageCapacity" : 32768,
                "sizeInBytes" : 32768
              }
            },
            "valueStorageSizeInBytes" : 27370
          }
        }
      },
      "markdown.header.anchor" : {
        "statsPerPhm" : {
          "markdown.header.anchor.storage" : {
            "persistentEnumeratorStatistics" : {
              "collisions" : 0,
              "values" : 2686,
              "dataFileSizeInBytes" : 44959,
              "storageSizeInBytes" : 21656,
              "btreeStatistics" : {
                "pages" : 1,
                "elements" : 2686,
                "height" : 1,
                "moves" : 0,
                "leafPages" : 1,
                "maxSearchStepsInRequest" : 13,
                "searchRequests" : 8140,
                "searchSteps" : 5705,
                "pageCapacity" : 32768,
                "sizeInBytes" : 32768
              }
            },
            "valueStorageSizeInBytes" : 61049
          }
        }
      },
      "properties.index" : {
        "statsPerPhm" : {
          "properties.index.storage" : {
            "persistentEnumeratorStatistics" : {
              "collisions" : 0,
              "values" : 568,
              "dataFileSizeInBytes" : 10424,
              "storageSizeInBytes" : 4680,
              "btreeStatistics" : {
                "pages" : 1,
                "elements" : 568,
                "height" : 1,
                "moves" : 0,
                "leafPages" : 1,
                "maxSearchStepsInRequest" : 2,
                "searchRequests" : 2261,
                "searchSteps" : 136,
                "pageCapacity" : 32768,
                "sizeInBytes" : 32768
              }
            },
            "valueStorageSizeInBytes" : 16091
          }
        }
      },
      "xmlProperties" : {
        "statsPerPhm" : {
          "xmlProperties.storage" : {
            "persistentEnumeratorStatistics" : {
              "collisions" : 0,
              "values" : 0,
              "dataFileSizeInBytes" : 0,
              "storageSizeInBytes" : 96,
              "btreeStatistics" : {
                "pages" : 0,
                "elements" : 0,
                "height" : 0,
                "moves" : 0,
                "leafPages" : 1,
                "maxSearchStepsInRequest" : 0,
                "searchRequests" : 0,
                "searchSteps" : 0,
                "pageCapacity" : 32768,
                "sizeInBytes" : 0
              }
            },
            "valueStorageSizeInBytes" : 0
          },
          "xmlProperties_inputs" : {
            "persistentEnumeratorStatistics" : {
              "collisions" : 0,
              "values" : 0,
              "dataFileSizeInBytes" : -1,
              "storageSizeInBytes" : 96,
              "btreeStatistics" : {
                "pages" : 0,
                "elements" : 0,
                "height" : 0,
                "moves" : 0,
                "leafPages" : 1,
                "maxSearchStepsInRequest" : 0,
                "searchRequests" : 0,
                "searchSteps" : 0,
                "pageCapacity" : 32768,
                "sizeInBytes" : 0
              }
            },
            "valueStorageSizeInBytes" : 0
          }
        }
      },
      "yaml.keys.name" : {
        "statsPerPhm" : {
          "yaml.keys.name.storage" : {
            "persistentEnumeratorStatistics" : {
              "collisions" : 0,
              "values" : 12492,
              "dataFileSizeInBytes" : 699493,
              "storageSizeInBytes" : 100256,
              "btreeStatistics" : {
                "pages" : 5,
                "elements" : 12492,
                "height" : 2,
                "moves" : 2,
                "leafPages" : 4,
                "maxSearchStepsInRequest" : 45,
                "searchRequests" : 36046,
                "searchSteps" : 52736,
                "pageCapacity" : 32768,
                "sizeInBytes" : 163840
              }
            },
            "valueStorageSizeInBytes" : 125693
          },
          "yaml.keys.name_inputs" : {
            "persistentEnumeratorStatistics" : {
              "collisions" : 0,
              "values" : 0,
              "dataFileSizeInBytes" : -1,
              "storageSizeInBytes" : 96,
              "btreeStatistics" : {
                "pages" : 1,
                "elements" : 57,
                "height" : 1,
                "moves" : 0,
                "leafPages" : 1,
                "maxSearchStepsInRequest" : 1,
                "searchRequests" : 547,
                "searchSteps" : 8,
                "pageCapacity" : 32768,
                "sizeInBytes" : 32768
              }
            },
            "valueStorageSizeInBytes" : 764520
          }
        }
      }
    },
    "otherStoragesStats" : {
      "statsPerPhm" : {
        "shared_indexes/shared.index.hashes.DomFileIndex/shared.index.hashes.DomFileIndex_storage.storage" : {
          "persistentEnumeratorStatistics" : {
            "collisions" : 0,
            "values" : 5,
            "dataFileSizeInBytes" : 25,
            "storageSizeInBytes" : 168,
            "btreeStatistics" : {
              "pages" : 1,
              "elements" : 5,
              "height" : 1,
              "moves" : 0,
              "leafPages" : 1,
              "maxSearchStepsInRequest" : 0,
              "searchRequests" : 12,
              "searchSteps" : 0,
              "pageCapacity" : 32768,
              "sizeInBytes" : 32768
            }
          },
          "valueStorageSizeInBytes" : 92
        },
        "shared_indexes/shared.index.hashes.FrameworkDetectionIndex/shared.index.hashes.FrameworkDetectionIndex_storage.storage" : {
          "persistentEnumeratorStatistics" : {
            "collisions" : 0,
            "values" : 0,
            "dataFileSizeInBytes" : 0,
            "storageSizeInBytes" : 96,
            "btreeStatistics" : {
              "pages" : 0,
              "elements" : 0,
              "height" : 0,
              "moves" : 0,
              "leafPages" : 1,
              "maxSearchStepsInRequest" : 0,
              "searchRequests" : 0,
              "searchSteps" : 0,
              "pageCapacity" : 32768,
              "sizeInBytes" : 0
            }
          },
          "valueStorageSizeInBytes" : 0
        },
        "shared_indexes/shared.index.hashes.IdIndex/shared.index.hashes.IdIndex_storage.storage" : {
          "persistentEnumeratorStatistics" : {
            "collisions" : 0,
            "values" : 6296,
            "dataFileSizeInBytes" : 31480,
            "storageSizeInBytes" : 50592,
            "btreeStatistics" : {
              "pages" : 3,
              "elements" : 6295,
              "height" : 2,
              "moves" : 0,
              "leafPages" : 2,
              "maxSearchStepsInRequest" : 42,
              "searchRequests" : 37018,
              "searchSteps" : 22384,
              "pageCapacity" : 32768,
              "sizeInBytes" : 98304
            }
          },
          "valueStorageSizeInBytes" : 262026
        },
        "shared_indexes/shared.index.hashes.Py.setuptools.namespace/shared.index.hashes.Py.setuptools.namespace_storage.storage" : {
          "persistentEnumeratorStatistics" : {
            "collisions" : 0,
            "values" : 0,
            "dataFileSizeInBytes" : 0,
            "storageSizeInBytes" : 96,
            "btreeStatistics" : {
              "pages" : 0,
              "elements" : 0,
              "height" : 0,
              "moves" : 0,
              "leafPages" : 1,
              "maxSearchStepsInRequest" : 0,
              "searchRequests" : 0,
              "searchSteps" : 0,
              "pageCapacity" : 32768,
              "sizeInBytes" : 0
            }
          },
          "valueStorageSizeInBytes" : 0
        },
        "shared_indexes/shared.index.hashes.RelaxSymbolIndex/shared.index.hashes.RelaxSymbolIndex_storage.storage" : {
          "persistentEnumeratorStatistics" : {
            "collisions" : 0,
            "values" : 5,
            "dataFileSizeInBytes" : 25,
            "storageSizeInBytes" : 168,
            "btreeStatistics" : {
              "pages" : 1,
              "elements" : 5,
              "height" : 1,
              "moves" : 0,
              "leafPages" : 1,
              "maxSearchStepsInRequest" : 0,
              "searchRequests" : 12,
              "searchSteps" : 0,
              "pageCapacity" : 32768,
              "sizeInBytes" : 32768
            }
          },
          "valueStorageSizeInBytes" : 92
        },
        "shared_indexes/shared.index.hashes.SchemaTypeInheritance/shared.index.hashes.SchemaTypeInheritance_storage.storage" : {
          "persistentEnumeratorStatistics" : {
            "collisions" : 0,
            "values" : 0,
            "dataFileSizeInBytes" : 0,
            "storageSizeInBytes" : 96,
            "btreeStatistics" : {
              "pages" : 0,
              "elements" : 0,
              "height" : 0,
              "moves" : 0,
              "leafPages" : 1,
              "maxSearchStepsInRequest" : 0,
              "searchRequests" : 0,
              "searchSteps" : 0,
              "pageCapacity" : 32768,
              "sizeInBytes" : 0
            }
          },
          "valueStorageSizeInBytes" : 0
        },
        "shared_indexes/shared.index.hashes.Stubs/shared.index.hashes.Stubs_storage.storage" : {
          "persistentEnumeratorStatistics" : {
            "collisions" : 0,
            "values" : 5716,
            "dataFileSizeInBytes" : 28580,
            "storageSizeInBytes" : 45944,
            "btreeStatistics" : {
              "pages" : 3,
              "elements" : 5716,
              "height" : 2,
              "moves" : 0,
              "leafPages" : 2,
              "maxSearchStepsInRequest" : 52,
              "searchRequests" : 40046,
              "searchSteps" : 21970,
              "pageCapacity" : 32768,
              "sizeInBytes" : 98304
            }
          },
          "valueStorageSizeInBytes" : 229199
        },
        "shared_indexes/shared.index.hashes.TodoIndex/shared.index.hashes.TodoIndex_storage.storage" : {
          "persistentEnumeratorStatistics" : {
            "collisions" : 0,
            "values" : 0,
            "dataFileSizeInBytes" : 0,
            "storageSizeInBytes" : 96,
            "btreeStatistics" : {
              "pages" : 0,
              "elements" : 0,
              "height" : 0,
              "moves" : 0,
              "leafPages" : 1,
              "maxSearchStepsInRequest" : 0,
              "searchRequests" : 0,
              "searchSteps" : 0,
              "pageCapacity" : 32768,
              "sizeInBytes" : 0
            }
          },
          "valueStorageSizeInBytes" : 0
        },
        "shared_indexes/shared.index.hashes.Trigram.Index/shared.index.hashes.Trigram.Index_storage.storage" : {
          "persistentEnumeratorStatistics" : {
            "collisions" : 0,
            "values" : 6298,
            "dataFileSizeInBytes" : 31490,
            "storageSizeInBytes" : 50608,
            "btreeStatistics" : {
              "pages" : 3,
              "elements" : 6297,
              "height" : 2,
              "moves" : 0,
              "leafPages" : 2,
              "maxSearchStepsInRequest" : 42,
              "searchRequests" : 36865,
              "searchSteps" : 22367,
              "pageCapacity" : 32768,
              "sizeInBytes" : 98304
            }
          },
          "valueStorageSizeInBytes" : 261986
        },
        "shared_indexes/shared.index.hashes.XmlNamespaces/shared.index.hashes.XmlNamespaces_storage.storage" : {
          "persistentEnumeratorStatistics" : {
            "collisions" : 0,
            "values" : 0,
            "dataFileSizeInBytes" : 0,
            "storageSizeInBytes" : 96,
            "btreeStatistics" : {
              "pages" : 0,
              "elements" : 0,
              "height" : 0,
              "moves" : 0,
              "leafPages" : 1,
              "maxSearchStepsInRequest" : 0,
              "searchRequests" : 0,
              "searchSteps" : 0,
              "pageCapacity" : 32768,
              "sizeInBytes" : 0
            }
          },
          "valueStorageSizeInBytes" : 0
        },
        "shared_indexes/shared.index.hashes.XmlTagNames/shared.index.hashes.XmlTagNames_storage.storage" : {
          "persistentEnumeratorStatistics" : {
            "collisions" : 0,
            "values" : 0,
            "dataFileSizeInBytes" : 0,
            "storageSizeInBytes" : 96,
            "btreeStatistics" : {
              "pages" : 0,
              "elements" : 0,
              "height" : 0,
              "moves" : 0,
              "leafPages" : 1,
              "maxSearchStepsInRequest" : 0,
              "searchRequests" : 0,
              "searchSteps" : 0,
              "pageCapacity" : 32768,
              "sizeInBytes" : 0
            }
          },
          "valueStorageSizeInBytes" : 0
        },
        "shared_indexes/shared.index.hashes.editorconfig.index.name/shared.index.hashes.editorconfig.index.name_storage.storage" : {
          "persistentEnumeratorStatistics" : {
            "collisions" : 0,
            "values" : 0,
            "dataFileSizeInBytes" : 0,
            "storageSizeInBytes" : 96,
            "btreeStatistics" : {
              "pages" : 0,
              "elements" : 0,
              "height" : 0,
              "moves" : 0,
              "leafPages" : 1,
              "maxSearchStepsInRequest" : 0,
              "searchRequests" : 0,
              "searchSteps" : 0,
              "pageCapacity" : 32768,
              "sizeInBytes" : 0
            }
          },
          "valueStorageSizeInBytes" : 0
        },
        "shared_indexes/shared.index.hashes.fileIncludes/shared.index.hashes.fileIncludes_storage.storage" : {
          "persistentEnumeratorStatistics" : {
            "collisions" : 0,
            "values" : 5,
            "dataFileSizeInBytes" : 25,
            "storageSizeInBytes" : 168,
            "btreeStatistics" : {
              "pages" : 1,
              "elements" : 5,
              "height" : 1,
              "moves" : 0,
              "leafPages" : 1,
              "maxSearchStepsInRequest" : 0,
              "searchRequests" : 12,
              "searchSteps" : 0,
              "pageCapacity" : 32768,
              "sizeInBytes" : 32768
            }
          },
          "valueStorageSizeInBytes" : 92
        },
        "shared_indexes/shared.index.hashes.html5.custom.attributes.index/shared.index.hashes.html5.custom.attributes.index_storage.storage" : {
          "persistentEnumeratorStatistics" : {
            "collisions" : 0,
            "values" : 4,
            "dataFileSizeInBytes" : 20,
            "storageSizeInBytes" : 160,
            "btreeStatistics" : {
              "pages" : 1,
              "elements" : 4,
              "height" : 1,
              "moves" : 0,
              "leafPages" : 1,
              "maxSearchStepsInRequest" : 0,
              "searchRequests" : 7,
              "searchSteps" : 0,
              "pageCapacity" : 32768,
              "sizeInBytes" : 32768
            }
          },
          "valueStorageSizeInBytes" : 70
        },
        "shared_indexes/shared.index.hashes.json.file.root.values/shared.index.hashes.json.file.root.values_storage.storage" : {
          "persistentEnumeratorStatistics" : {
            "collisions" : 0,
            "values" : 10,
            "dataFileSizeInBytes" : 50,
            "storageSizeInBytes" : 208,
            "btreeStatistics" : {
              "pages" : 1,
              "elements" : 10,
              "height" : 1,
              "moves" : 0,
              "leafPages" : 1,
              "maxSearchStepsInRequest" : 0,
              "searchRequests" : 19,
              "searchSteps" : 0,
              "pageCapacity" : 32768,
              "sizeInBytes" : 32768
            }
          },
          "valueStorageSizeInBytes" : 99
        },
        "shared_indexes/shared.index.hashes.xmlProperties/shared.index.hashes.xmlProperties_storage.storage" : {
          "persistentEnumeratorStatistics" : {
            "collisions" : 0,
            "values" : 5,
            "dataFileSizeInBytes" : 25,
            "storageSizeInBytes" : 168,
            "btreeStatistics" : {
              "pages" : 1,
              "elements" : 5,
              "height" : 1,
              "moves" : 0,
              "leafPages" : 1,
              "maxSearchStepsInRequest" : 0,
              "searchRequests" : 12,
              "searchSteps" : 0,
              "pageCapacity" : 32768,
              "sizeInBytes" : 32768
            }
          },
          "valueStorageSizeInBytes" : 92
        },
        "shared_indexes/shared.index.hashes.yaml.keys.name/shared.index.hashes.yaml.keys.name_storage.storage" : {
          "persistentEnumeratorStatistics" : {
            "collisions" : 0,
            "values" : 0,
            "dataFileSizeInBytes" : 0,
            "storageSizeInBytes" : 96,
            "btreeStatistics" : {
              "pages" : 0,
              "elements" : 0,
              "height" : 0,
              "moves" : 0,
              "leafPages" : 1,
              "maxSearchStepsInRequest" : 0,
              "searchRequests" : 0,
              "searchSteps" : 0,
              "pageCapacity" : 32768,
              "sizeInBytes" : 0
            }
          },
          "valueStorageSizeInBytes" : 0
        }
      },
      "statsPerEnumerator" : {
        "rep.names" : {
          "collisions" : 0,
          "values" : 36,
          "dataFileSizeInBytes" : 734,
          "storageSizeInBytes" : 96,
          "btreeStatistics" : {
            "pages" : 1,
            "elements" : 36,
            "height" : 1,
            "moves" : 0,
            "leafPages" : 1,
            "maxSearchStepsInRequest" : 0,
            "searchRequests" : 107,
            "searchSteps" : 0,
            "pageCapacity" : 32768,
            "sizeInBytes" : 32768
          }
        }
      }
    }
  },
  "otherStorageStats" : {
    "statsPerPhm" : {
      "$USER_HOME$/Library/Caches/JetBrains/PyCharmCE2023.2/vcs-log/anmol_70fb4147_eaf1d68e/index/committers.26" : {
        "persistentEnumeratorStatistics" : {
          "collisions" : 0,
          "values" : 0,
          "dataFileSizeInBytes" : -1,
          "storageSizeInBytes" : 96,
          "btreeStatistics" : {
            "pages" : 1,
            "elements" : 403,
            "height" : 1,
            "moves" : 0,
            "leafPages" : 1,
            "maxSearchStepsInRequest" : 2,
            "searchRequests" : 846,
            "searchSteps" : 8,
            "pageCapacity" : 32768,
            "sizeInBytes" : 32768
          }
        },
        "valueStorageSizeInBytes" : 2467
      },
      "$USER_HOME$/Library/Caches/JetBrains/PyCharmCE2023.2/vcs-log/anmol_70fb4147_eaf1d68e/index/messages.26" : {
        "persistentEnumeratorStatistics" : {
          "collisions" : 0,
          "values" : 0,
          "dataFileSizeInBytes" : -1,
          "storageSizeInBytes" : 96,
          "btreeStatistics" : {
            "pages" : 3,
            "elements" : 4484,
            "height" : 2,
            "moves" : 0,
            "leafPages" : 2,
            "maxSearchStepsInRequest" : 115,
            "searchRequests" : 27352,
            "searchSteps" : 5866,
            "pageCapacity" : 32768,
            "sizeInBytes" : 98304
          }
        },
        "valueStorageSizeInBytes" : 267574
      },
      "$USER_HOME$/Library/Caches/JetBrains/PyCharmCE2023.2/vcs-log/anmol_70fb4147_eaf1d68e/index/parents.26" : {
        "persistentEnumeratorStatistics" : {
          "collisions" : 0,
          "values" : 0,
          "dataFileSizeInBytes" : -1,
          "storageSizeInBytes" : 96,
          "btreeStatistics" : {
            "pages" : 3,
            "elements" : 4484,
            "height" : 2,
            "moves" : 0,
            "leafPages" : 2,
            "maxSearchStepsInRequest" : 115,
            "searchRequests" : 30698,
            "searchSteps" : 5462,
            "pageCapacity" : 32768,
            "sizeInBytes" : 98304
          }
        },
        "valueStorageSizeInBytes" : 32673
      },
      "$USER_HOME$/Library/Caches/JetBrains/PyCharmCE2023.2/vcs-log/anmol_70fb4147_eaf1d68e/index/paths.26.storage" : {
        "persistentEnumeratorStatistics" : {
          "collisions" : 0,
          "values" : 0,
          "dataFileSizeInBytes" : -1,
          "storageSizeInBytes" : 96,
          "btreeStatistics" : {
            "pages" : 3,
            "elements" : 4456,
            "height" : 2,
            "moves" : 0,
            "leafPages" : 2,
            "maxSearchStepsInRequest" : 48,
            "searchRequests" : 14675,
            "searchSteps" : 20460,
            "pageCapacity" : 32768,
            "sizeInBytes" : 98304
          }
        },
        "valueStorageSizeInBytes" : 199119
      },
      "$USER_HOME$/Library/Caches/JetBrains/PyCharmCE2023.2/vcs-log/anmol_70fb4147_eaf1d68e/index/renames-map.26" : {
        "persistentEnumeratorStatistics" : {
          "collisions" : 0,
          "values" : 127,
          "dataFileSizeInBytes" : 1016,
          "storageSizeInBytes" : 1144,
          "btreeStatistics" : {
            "pages" : 1,
            "elements" : 127,
            "height" : 1,
            "moves" : 0,
            "leafPages" : 1,
            "maxSearchStepsInRequest" : 1,
            "searchRequests" : 3167,
            "searchSteps" : 123,
            "pageCapacity" : 32768,
            "sizeInBytes" : 32768
          }
        },
        "valueStorageSizeInBytes" : 15648
      },
      "$USER_HOME$/Library/Caches/JetBrains/PyCharmCE2023.2/vcs-log/anmol_70fb4147_eaf1d68e/index/timestamps.26" : {
        "persistentEnumeratorStatistics" : {
          "collisions" : 0,
          "values" : 0,
          "dataFileSizeInBytes" : -1,
          "storageSizeInBytes" : 96,
          "btreeStatistics" : {
            "pages" : 3,
            "elements" : 4484,
            "height" : 2,
            "moves" : 0,
            "leafPages" : 2,
            "maxSearchStepsInRequest" : 115,
            "searchRequests" : 12734,
            "searchSteps" : 5462,
            "pageCapacity" : 32768,
            "sizeInBytes" : 98304
          }
        },
        "valueStorageSizeInBytes" : 80761
      },
      "$USER_HOME$/Library/Caches/JetBrains/PyCharmCE2023.2/vcs-log/anmol_70fb4147_eaf1d68e/index/trigrams.26.storage" : {
        "persistentEnumeratorStatistics" : {
          "collisions" : 0,
          "values" : 0,
          "dataFileSizeInBytes" : -1,
          "storageSizeInBytes" : 96,
          "btreeStatistics" : {
            "pages" : 1,
            "elements" : 3508,
            "height" : 1,
            "moves" : 0,
            "leafPages" : 1,
            "maxSearchStepsInRequest" : 38,
            "searchRequests" : 11436,
            "searchSteps" : 14706,
            "pageCapacity" : 32768,
            "sizeInBytes" : 32768
          }
        },
        "valueStorageSizeInBytes" : 300870
      },
      "$USER_HOME$/Library/Caches/JetBrains/PyCharmCE2023.2/vcs-log/anmol_70fb4147_eaf1d68e/index/users.26.storage" : {
        "persistentEnumeratorStatistics" : {
          "collisions" : 0,
          "values" : 0,
          "dataFileSizeInBytes" : -1,
          "storageSizeInBytes" : 96,
          "btreeStatistics" : {
            "pages" : 1,
            "elements" : 105,
            "height" : 1,
            "moves" : 0,
            "leafPages" : 1,
            "maxSearchStepsInRequest" : 0,
            "searchRequests" : 232,
            "searchSteps" : 0,
            "pageCapacity" : 32768,
            "sizeInBytes" : 32768
          }
        },
        "valueStorageSizeInBytes" : 8038
      },
      "$USER_HOME$/Library/Caches/JetBrains/PyCharmCE2023.2/vcs-log/anmol_70fb4147_eaf1d68e/index/users.idx.26" : {
        "persistentEnumeratorStatistics" : {
          "collisions" : 0,
          "values" : 0,
          "dataFileSizeInBytes" : -1,
          "storageSizeInBytes" : 96,
          "btreeStatistics" : {
            "pages" : 3,
            "elements" : 4484,
            "height" : 2,
            "moves" : 0,
            "leafPages" : 2,
            "maxSearchStepsInRequest" : 115,
            "searchRequests" : 17205,
            "searchSteps" : 8193,
            "pageCapacity" : 32768,
            "sizeInBytes" : 98304
          }
        },
        "valueStorageSizeInBytes" : 31437
      },
      "DomFileIndex/DomFileIndex.forward" : {
        "persistentEnumeratorStatistics" : {
          "collisions" : 0,
          "values" : 0,
          "dataFileSizeInBytes" : -1,
          "storageSizeInBytes" : 96,
          "btreeStatistics" : {
            "pages" : 1,
            "elements" : 6,
            "height" : 1,
            "moves" : 0,
            "leafPages" : 1,
            "maxSearchStepsInRequest" : 0,
            "searchRequests" : 11,
            "searchSteps" : 0,
            "pageCapacity" : 32768,
            "sizeInBytes" : 32768
          }
        },
        "valueStorageSizeInBytes" : 279
      },
      "DomFileIndex/DomFileIndex.storage" : {
        "persistentEnumeratorStatistics" : {
          "collisions" : 0,
          "values" : 8,
          "dataFileSizeInBytes" : 194,
          "storageSizeInBytes" : 192,
          "btreeStatistics" : {
            "pages" : 1,
            "elements" : 8,
            "height" : 1,
            "moves" : 0,
            "leafPages" : 1,
            "maxSearchStepsInRequest" : 0,
            "searchRequests" : 15,
            "searchSteps" : 0,
            "pageCapacity" : 32768,
            "sizeInBytes" : 32768
          }
        },
        "valueStorageSizeInBytes" : 95
      },
      "IdIndex/IdIndex.storage" : {
        "persistentEnumeratorStatistics" : {
          "collisions" : 0,
          "values" : 0,
          "dataFileSizeInBytes" : -1,
          "storageSizeInBytes" : 96,
          "btreeStatistics" : {
            "pages" : 267,
            "elements" : 501154,
            "height" : 2,
            "moves" : 9,
            "leafPages" : 266,
            "maxSearchStepsInRequest" : 170,
            "searchRequests" : 2479986,
            "searchSteps" : 3578347,
            "pageCapacity" : 32768,
            "sizeInBytes" : 8749056
          }
        },
        "valueStorageSizeInBytes" : 10221334
      },
      "Stubs/Py.class.attributes/Py.class.attributes.storage" : {
        "persistentEnumeratorStatistics" : {
          "collisions" : 18,
          "values" : 53341,
          "dataFileSizeInBytes" : 962748,
          "storageSizeInBytes" : 431784,
          "btreeStatistics" : {
            "pages" : 20,
            "elements" : 53332,
            "height" : 2,
            "moves" : 78,
            "leafPages" : 19,
            "maxSearchStepsInRequest" : 71,
            "searchRequests" : 173011,
            "searchSteps" : 272587,
            "pageCapacity" : 32768,
            "sizeInBytes" : 655360
          }
        },
        "valueStorageSizeInBytes" : 801157
      },
      "Stubs/Py.class.shortName/Py.class.shortName.storage" : {
        "persistentEnumeratorStatistics" : {
          "collisions" : 12,
          "values" : 15157,
          "dataFileSizeInBytes" : 230349,
          "storageSizeInBytes" : 125712,
          "btreeStatistics" : {
            "pages" : 7,
            "elements" : 15151,
            "height" : 2,
            "moves" : 5,
            "leafPages" : 6,
            "maxSearchStepsInRequest" : 69,
            "searchRequests" : 48738,
            "searchSteps" : 76783,
            "pageCapacity" : 32768,
            "sizeInBytes" : 229376
          }
        },
        "valueStorageSizeInBytes" : 186625
      },
      "Stubs/Py.class.shortNameInsensitive/Py.class.shortNameInsensitive.storage" : {
        "persistentEnumeratorStatistics" : {
          "collisions" : 6,
          "values" : 14953,
          "dataFileSizeInBytes" : 228877,
          "storageSizeInBytes" : 124080,
          "btreeStatistics" : {
            "pages" : 8,
            "elements" : 14950,
            "height" : 2,
            "moves" : 8,
            "leafPages" : 7,
            "maxSearchStepsInRequest" : 57,
            "searchRequests" : 52015,
            "searchSteps" : 77528,
            "pageCapacity" : 32768,
            "sizeInBytes" : 262144
          }
        },
        "valueStorageSizeInBytes" : 185019
      },
      "Stubs/Py.class.super/Py.class.super.storage" : {
        "persistentEnumeratorStatistics" : {
          "collisions" : 2,
          "values" : 2983,
          "dataFileSizeInBytes" : 41873,
          "storageSizeInBytes" : 28128,
          "btreeStatistics" : {
            "pages" : 1,
            "elements" : 2982,
            "height" : 1,
            "moves" : 0,
            "leafPages" : 1,
            "maxSearchStepsInRequest" : 26,
            "searchRequests" : 5965,
            "searchSteps" : 4700,
            "pageCapacity" : 32768,
            "sizeInBytes" : 32768
          }
        },
        "valueStorageSizeInBytes" : 50895
      },
      "Stubs/Py.function.shortName/Py.function.shortName.storage" : {
        "persistentEnumeratorStatistics" : {
          "collisions" : 8,
          "values" : 49841,
          "dataFileSizeInBytes" : 938378,
          "storageSizeInBytes" : 403728,
          "btreeStatistics" : {
            "pages" : 20,
            "elements" : 49837,
            "height" : 2,
            "moves" : 83,
            "leafPages" : 19,
            "maxSearchStepsInRequest" : 60,
            "searchRequests" : 166011,
            "searchSteps" : 264558,
            "pageCapacity" : 32768,
            "sizeInBytes" : 655360
          }
        },
        "valueStorageSizeInBytes" : 764893
      },
      "Stubs/Py.module.attribute/Py.module.attribute.storage" : {
        "persistentEnumeratorStatistics" : {
          "collisions" : 24,
          "values" : 33433,
          "dataFileSizeInBytes" : 503531,
          "storageSizeInBytes" : 272208,
          "btreeStatistics" : {
            "pages" : 14,
            "elements" : 33421,
            "height" : 2,
            "moves" : 37,
            "leafPages" : 13,
            "maxSearchStepsInRequest" : 60,
            "searchRequests" : 111085,
            "searchSteps" : 168513,
            "pageCapacity" : 32768,
            "sizeInBytes" : 458752
          }
        },
        "valueStorageSizeInBytes" : 412745
      },
      "Stubs/Py.variable.shortName/Py.variable.shortName.storage" : {
        "persistentEnumeratorStatistics" : {
          "collisions" : 18,
          "values" : 13680,
          "dataFileSizeInBytes" : 197676,
          "storageSizeInBytes" : 113872,
          "btreeStatistics" : {
            "pages" : 6,
            "elements" : 13671,
            "height" : 2,
            "moves" : 2,
            "leafPages" : 5,
            "maxSearchStepsInRequest" : 52,
            "searchRequests" : 42099,
            "searchSteps" : 66119,
            "pageCapacity" : 32768,
            "sizeInBytes" : 196608
          }
        },
        "valueStorageSizeInBytes" : 163225
      },
      "Stubs/Python.Decorator/Python.Decorator.storage" : {
        "persistentEnumeratorStatistics" : {
          "collisions" : 0,
          "values" : 599,
          "dataFileSizeInBytes" : 11330,
          "storageSizeInBytes" : 4928,
          "btreeStatistics" : {
            "pages" : 1,
            "elements" : 599,
            "height" : 1,
            "moves" : 0,
            "leafPages" : 1,
            "maxSearchStepsInRequest" : 3,
            "searchRequests" : 1197,
            "searchSteps" : 106,
            "pageCapacity" : 32768,
            "sizeInBytes" : 32768
          }
        },
        "valueStorageSizeInBytes" : 15342
      },
      "Stubs/Stubs.storage" : {
        "persistentEnumeratorStatistics" : {
          "collisions" : 0,
          "values" : 0,
          "dataFileSizeInBytes" : -1,
          "storageSizeInBytes" : 96,
          "btreeStatistics" : {
            "pages" : 6,
            "elements" : 10335,
            "height" : 2,
            "moves" : 0,
            "leafPages" : 5,
            "maxSearchStepsInRequest" : 347,
            "searchRequests" : 45744,
            "searchSteps" : 19288,
            "pageCapacity" : 32768,
            "sizeInBytes" : 196608
          }
        },
        "valueStorageSizeInBytes" : 52960233
      },
      "Stubs/markdown.header.anchor/markdown.header.anchor.storage" : {
        "persistentEnumeratorStatistics" : {
          "collisions" : 0,
          "values" : 17,
          "dataFileSizeInBytes" : 281,
          "storageSizeInBytes" : 264,
          "btreeStatistics" : {
            "pages" : 1,
            "elements" : 17,
            "height" : 1,
            "moves" : 0,
            "leafPages" : 1,
            "maxSearchStepsInRequest" : 0,
            "searchRequests" : 33,
            "searchSteps" : 0,
            "pageCapacity" : 32768,
            "sizeInBytes" : 32768
          }
        },
        "valueStorageSizeInBytes" : 125
      },
      "Stubs/markdown.header/markdown.header.storage" : {
        "persistentEnumeratorStatistics" : {
          "collisions" : 0,
          "values" : 17,
          "dataFileSizeInBytes" : 291,
          "storageSizeInBytes" : 264,
          "btreeStatistics" : {
            "pages" : 1,
            "elements" : 17,
            "height" : 1,
            "moves" : 0,
            "leafPages" : 1,
            "maxSearchStepsInRequest" : 0,
            "searchRequests" : 33,
            "searchSteps" : 0,
            "pageCapacity" : 32768,
            "sizeInBytes" : 32768
          }
        },
        "valueStorageSizeInBytes" : 125
      },
      "Trigram.Index/Trigram.Index.storage" : {
        "persistentEnumeratorStatistics" : {
          "collisions" : 0,
          "values" : 0,
          "dataFileSizeInBytes" : -1,
          "storageSizeInBytes" : 96,
          "btreeStatistics" : {
            "pages" : 28,
            "elements" : 51496,
            "height" : 2,
            "moves" : 0,
            "leafPages" : 27,
            "maxSearchStepsInRequest" : 455,
            "searchRequests" : 250297,
            "searchSteps" : 568776,
            "pageCapacity" : 32768,
            "sizeInBytes" : 917504
          }
        },
        "valueStorageSizeInBytes" : 7684575
      },
      "json.file.root.values/json.file.root.values.forward" : {
        "persistentEnumeratorStatistics" : {
          "collisions" : 0,
          "values" : 0,
          "dataFileSizeInBytes" : -1,
          "storageSizeInBytes" : 96,
          "btreeStatistics" : {
            "pages" : 1,
            "elements" : 11,
            "height" : 1,
            "moves" : 0,
            "leafPages" : 1,
            "maxSearchStepsInRequest" : 0,
            "searchRequests" : 21,
            "searchSteps" : 0,
            "pageCapacity" : 32768,
            "sizeInBytes" : 32768
          }
        },
        "valueStorageSizeInBytes" : 863
      },
      "json.file.root.values/json.file.root.values.storage" : {
        "persistentEnumeratorStatistics" : {
          "collisions" : 0,
          "values" : 3,
          "dataFileSizeInBytes" : 63,
          "storageSizeInBytes" : 152,
          "btreeStatistics" : {
            "pages" : 1,
            "elements" : 3,
            "height" : 1,
            "moves" : 0,
            "leafPages" : 1,
            "maxSearchStepsInRequest" : 0,
            "searchRequests" : 5,
            "searchSteps" : 0,
            "pageCapacity" : 32768,
            "sizeInBytes" : 32768
          }
        },
        "valueStorageSizeInBytes" : 133
      }
    },
    "statsPerEnumerator" : {
      "$USER_HOME$/Library/Caches/JetBrains/PyCharmCE2023.2/vcs-log/anmol_70fb4147_eaf1d68e/hashes/storage.8" : {
        "collisions" : 0,
        "values" : 4485,
        "dataFileSizeInBytes" : 116610,
        "storageSizeInBytes" : 96,
        "btreeStatistics" : {
          "pages" : 3,
          "elements" : 4485,
          "height" : 2,
          "moves" : 0,
          "leafPages" : 2,
          "maxSearchStepsInRequest" : 32,
          "searchRequests" : 45421,
          "searchSteps" : 31531,
          "pageCapacity" : 32768,
          "sizeInBytes" : 98304
        }
      },
      "$USER_HOME$/Library/Caches/JetBrains/PyCharmCE2023.2/vcs-log/anmol_70fb4147_eaf1d68e/index/paths-ids.26" : {
        "collisions" : 0,
        "values" : 4456,
        "dataFileSizeInBytes" : 236651,
        "storageSizeInBytes" : 96,
        "btreeStatistics" : {
          "pages" : 3,
          "elements" : 4456,
          "height" : 2,
          "moves" : 0,
          "leafPages" : 2,
          "maxSearchStepsInRequest" : 32,
          "searchRequests" : 94807,
          "searchSteps" : 44569,
          "pageCapacity" : 32768,
          "sizeInBytes" : 98304
        }
      },
      "$USER_HOME$/Library/Caches/JetBrains/PyCharmCE2023.2/vcs-log/anmol_70fb4147_eaf1d68e/index/users-ids.26" : {
        "collisions" : 0,
        "values" : 106,
        "dataFileSizeInBytes" : 4162,
        "storageSizeInBytes" : 96,
        "btreeStatistics" : {
          "pages" : 1,
          "elements" : 106,
          "height" : 1,
          "moves" : 0,
          "leafPages" : 1,
          "maxSearchStepsInRequest" : 1,
          "searchRequests" : 5033,
          "searchSteps" : 8,
          "pageCapacity" : 32768,
          "sizeInBytes" : 32768
        }
      },
      "$USER_HOME$/Library/Caches/JetBrains/PyCharmCE2023.2/vcs-log/anmol_70fb4147_eaf1d68e/refs/storage.10" : {
        "collisions" : 0,
        "values" : 124,
        "dataFileSizeInBytes" : 5051,
        "storageSizeInBytes" : 96,
        "btreeStatistics" : {
          "pages" : 1,
          "elements" : 124,
          "height" : 1,
          "moves" : 0,
          "leafPages" : 1,
          "maxSearchStepsInRequest" : 2,
          "searchRequests" : 564,
          "searchSteps" : 16,
          "pageCapacity" : 32768,
          "sizeInBytes" : 32768
        }
      },
      "$USER_HOME$/Library/Caches/JetBrains/PyCharmCE2023.2/vcs-users/70fb4147.2" : {
        "collisions" : 0,
        "values" : 106,
        "dataFileSizeInBytes" : 4162,
        "storageSizeInBytes" : 96,
        "btreeStatistics" : {
          "pages" : 1,
          "elements" : 106,
          "height" : 1,
          "moves" : 0,
          "leafPages" : 1,
          "maxSearchStepsInRequest" : 1,
          "searchRequests" : 4410,
          "searchSteps" : 12,
          "pageCapacity" : 32768,
          "sizeInBytes" : 32768
        }
      },
      "Stubs/serializerNames/names" : {
        "collisions" : 0,
        "values" : 36,
        "dataFileSizeInBytes" : 734,
        "storageSizeInBytes" : 96,
        "btreeStatistics" : {
          "pages" : 1,
          "elements" : 36,
          "height" : 1,
          "moves" : 0,
          "leafPages" : 1,
          "maxSearchStepsInRequest" : 0,
          "searchRequests" : 71,
          "searchSteps" : 0,
          "pageCapacity" : 32768,
          "sizeInBytes" : 32768
        }
      },
      "hashes" : {
        "collisions" : 0,
        "values" : 12703,
        "dataFileSizeInBytes" : 254060,
        "storageSizeInBytes" : 96,
        "btreeStatistics" : {
          "pages" : 5,
          "elements" : 12703,
          "height" : 2,
          "moves" : 1,
          "leafPages" : 4,
          "maxSearchStepsInRequest" : 46,
          "searchRequests" : 90231,
          "searchSteps" : 110732,
          "pageCapacity" : 32768,
          "sizeInBytes" : 163840
        }
      }
    }
  }
}