{"url":"https://cloud.jarvis.live/panel/eoi-management/7382","datetime":"06-12-2023 14:45:30","feed":"Camera 1 1701841490493","location":"FM Brooks","frame_width":1280,"frame_height":720,"data":[{"name":"person_analytics","rois":[{"points":[{"x":0.8888888888888888,"y":2.8609271523178808},{"x":1279.111111111111,"y":2.8609271523178808},{"x":1279.111111111111,"y":707.6026490066225},{"x":0.8888888888888888,"y":707.6026490066225}],"dimension":{"width":1280,"height":720},"shape":"polygon","color":"red","name":"R-1","index":1,"info":{"name":"R-1"}},{"points":[{"x":0,"y":3.814569536423841},{"x":1279.111111111111,"y":3.814569536423841},{"x":1279.111111111111,"y":657.0596026490066},{"x":0,"y":657.0596026490066}],"dimension":{"width":1280,"height":720},"shape":"polygon","color":"yellow","name":"R-2","index":2,"info":{"name":"R-2"}},{"points":[{"x":72.88888888888889,"y":484.4503311258278},{"x":1247.111111111111,"y":536.9006622516556}],"dimension":{"width":1280,"height":720},"shape":"line","color":"#000","name":"entry_line","index":3,"info":{"name":"entry_line"}},{"points":[{"x":16,"y":369.0596026490066},{"x":1244.4444444444443,"y":401.4834437086093}],"dimension":{"width":1280,"height":720},"shape":"line","color":"#000","name":"middle_line","index":4,"info":{"name":"middle_line"}},{"points":[{"x":0,"y":258.4370860927152},{"x":1279.111111111111,"y":289.9072847682119}],"dimension":{"width":1280,"height":720},"shape":"line","color":"#000","name":"exit_line","index":5,"info":{"name":"exit_line"}}]}]}